opcodetools/__init__.py
opcodetools/asm.py
opcodetools/dasm.py
opcodetools/dump.py
opcodetools/assembler/__init__.py
opcodetools/assembler/assembler.py
opcodetools/cpu/__init__.py
opcodetools/cpu/base_assembly.py
opcodetools/cpu/base_cpu.py
opcodetools/cpu/base_disassembly.py
opcodetools/cpu/cpu_6502.py
opcodetools/cpu/cpu_6803.py
opcodetools/cpu/cpu_6809.py
opcodetools/cpu/cpu_8052.py
opcodetools/cpu/cpu_DVG.py
opcodetools/cpu/cpu_Z80.py
opcodetools/cpu/cpu_Z80GB.py
opcodetools/cpu/cpu_manager.py
opcodetools/cpu/dev_format.py
opcodetools/cpu/opcode.py
opcodetools/disassembler/__init__.py
opcodetools/disassembler/binary.py
opcodetools-1.5.dist-info/LICENSE
opcodetools-1.5.dist-info/METADATA
opcodetools-1.5.dist-info/WHEEL
opcodetools-1.5.dist-info/top_level.txt
opcodetools-1.5.dist-info/RECORD
