Metadata-Version: 2.1
Name: opcodetools
Version: 1.5
Summary: Assemblers/Disassemblers for retro processors (Z80, 6502, 6809, etc)
Home-page: https://github.com/topherCantrell/opcodetools
Author: Chris Cantrell
Author-email: topherCantrell@gmail.com
License: UNKNOWN
Platform: UNKNOWN
Classifier: Programming Language :: Python :: 3
Classifier: License :: OSI Approved :: MIT License
Classifier: Operating System :: OS Independent
Requires-Python: >=3.8
